{
  "appPageId" : "55356af3-d13c-4f4f-bf46-0132122655b4",
  "componentName" : "siteforce:sldsOneColLayout",
  "id" : "d402a387-7e7b-43af-8cc6-26d62244dbe6",
  "label" : "Stream List",
  "regions" : [ {
    "components" : [ {
      "componentAttributes" : { },
      "componentName" : "forceCommunity:streamList",
      "id" : "684dda0b-9789-4c4b-b258-f01400291992",
      "renderPriority" : "NEUTRAL",
      "renditionMap" : { },
      "type" : "component"
    } ],
    "id" : "60ba63fe-b995-4989-8c2e-eae7cc2538fb",
    "regionName" : "content",
    "type" : "region"
  } ],
  "themeLayoutType" : "Inner",
  "type" : "view",
  "viewType" : "list-0Fq"
}